pylayout/__init__.py
pylayout/_lang_layouts.py
pylayout/pylayout.py
pylayout-0.1.2.dist-info/licenses/LICENCE.txt
pylayout-0.1.2.dist-info/METADATA
pylayout-0.1.2.dist-info/WHEEL
pylayout-0.1.2.dist-info/top_level.txt
pylayout-0.1.2.dist-info/RECORD
