Metadata-Version: 2.4
Name: pylayout
Version: 0.1.2
Summary: Module to get and set keyboard layout
Author-email: Roman Smolnyk <poma23324@gmail.com>
Project-URL: Homepage, https://github.com/roman-smolnyk/python-pylayout.git
Keywords: keyboard,layout
Classifier: Programming Language :: Python :: 3
Classifier: License :: OSI Approved :: MIT License
Classifier: Operating System :: OS Independent
Requires-Python: >=3.8
License-File: LICENCE.txt
Requires-Dist: pywin32; platform_system == "Windows"
Dynamic: license-file
